net_puppy/__init__.py
net_puppy/core.py
net_puppy-0.0.2.dist-info/LICENSE
net_puppy-0.0.2.dist-info/METADATA
net_puppy-0.0.2.dist-info/WHEEL
net_puppy-0.0.2.dist-info/top_level.txt
net_puppy-0.0.2.dist-info/RECORD
