Metadata-Version: 2.1
Name: net-puppy
Version: 0.0.2
Summary: A network controlled terminal interface
Home-page: https://github.com/vishal-keshav/net_puppy
Author: Vishal Keshav
Author-email: vishal.keshav.1993@gmail.com
License: UNKNOWN
Platform: UNKNOWN
Classifier: Programming Language :: Python :: 3.6
Classifier: License :: OSI Approved :: MIT License
Classifier: Operating System :: POSIX :: Linux
